{"w":19,"h":19,"type":"rescue","rescueMode":{"type":"mode23","pos":"3a3a","size":9,"value":100,"count":5},"bricks":[{"type":"brick6","value":0,"color":0,"loca":["3F3H","3lA3","3l2J","3HFA","32AH","32J3","FAJH","FmH3","F3FJ","FFml","FFaA","FlHH","F1l3","FHmJ","F33J","Fm13","FA2H","3223","3HaH","3H3A"]},{"type":"brick1","value":900,"color":9,"loca":["331A","FHm2","FFmF","33la","FHmH","FFm3","FlHl","3l2H","3lAA","33lJ","3113","FHm1","FFmm","FlHF","33l2","FHml","FFmA","FlH3","3FaJ","3l2l","33lH","3F33","FHmF","FFAa","FlHm","33l1","FHm3","FFAJ","FlHA","3l23","3FaH","33ll","31lJ","FHmm","FFA2","Fl1a","33lF","FHmA","FFAH","Fl1J","3Fal","3l2A","33l3","3FmJ","FHAa","FFA1","Fl12","33lm","FHAJ","FFAl","Fl1H","3lHJ","3Fa3","33lA","31ll","FHA2","FFAF","Fl11","3Ha1","3Hma","33Fa","FHAH","FFA3","Fl1l","3HmJ","3Hal","33FJ","Fm1A","3FaA","3lHH","3Fml","3JlH","FHA1","3Jl1","Fl1F","3Hm2","3HaF","Fmla","33F2","FHAl","FFAA","Fl13","3HmH","3Ha3","32HJ","3Jll","FmlJ","3lHl","3FJJ","33FH","3aaH","31lA","3a3A","FA23","F33l","FF2H"]},{"type":"brick1","value":300,"color":9,"loca":["3aaa","3aaJ"]}],"props":[{"type":"scatter","value":50,"color":0,"loca":["311l","3a33"]}],"props2":[]}