{"ver":1,"w":15,"h":15,"type":"task","bricks":[{"type":"magnet","value":100,"color":2,"size_w":1,"size_h":1,"loca":["mJFH"]},{"type":"puzzle","value":45,"color":4,"size_w":2,"size_h":2,"loca":["ml21","3311"]},{"type":"brick1","value":500,"color":4,"size_w":1,"size_h":1,"loca":["m1F1","3mF1"]},{"type":"brick1","value":200,"color":1,"size_w":2,"size_h":1,"loca":["m221","ma11"]},{"type":"brick3","value":900,"color":3,"size_w":1,"size_h":1,"loca":["m22l"]},{"type":"brick2","value":900,"color":3,"size_w":1,"size_h":1,"loca":["mJal"]},{"type":"brick1","value":50,"color":2,"size_w":1,"size_h":1,"loca":["3mF3","m1F3"]},{"type":"orange","value":20,"color":3,"size_w":1,"size_h":1,"loca":["3Am3","mH13"]},{"type":"brick1","value":800,"color":3,"size_w":1,"size_h":6,"loca":["3A2m","m1am"]},{"type":"brick1","value":500,"color":3,"size_w":2,"size_h":2,"loca":["mJFm","mJJ2"]},{"type":"brick1","value":900,"color":3,"size_w":1,"size_h":1,"loca":["331A","mlmA"]},{"type":"brick1","value":400,"color":0,"size_w":1,"size_h":6,"loca":["mala","m2Aa"]},{"type":"brick1","value":180,"color":2,"size_w":1,"size_h":5,"loca":["mlHa"]},{"type":"brick1","value":200,"color":1,"size_w":1,"size_h":5,"loca":["3mJa"]},{"type":"orange","value":15,"color":0,"size_w":1,"size_h":1,"loca":["33lH","3mJH","3m3H","3AHH","3AAH","mlAH","mlHH","m13H","m1JH","mHlH"]}],"props":[{"type":"bomb1","value":40,"color":0,"size_w":1,"size_h":1,"loca":["mJF1"]},{"type":"bomb1","value":500,"color":0,"size_w":1,"size_h":1,"loca":["m1Fl","3mFl","mlmF","331F"]},{"type":"bomb-","value":900,"color":0,"size_w":1,"size_h":1,"loca":["mJFl"]},{"type":"bomb-","value":500,"color":0,"size_w":1,"size_h":1,"loca":["m1FF","3mFF"]},{"type":"bomb-","value":50,"color":0,"size_w":1,"size_h":1,"loca":["m2m3","ma13"]},{"type":"addBall","value":45,"color":0,"size_w":1,"size_h":1,"loca":["m1Fm","m1FA","m13a","m13J","m132"]},{"type":"addBall","value":100,"color":0,"size_w":1,"size_h":1,"loca":["3mFm","3mFA","3m3a","3m3J","3m32"]},{"type":"lock2","value":0,"color":0,"size_w":1,"size_h":1,"loca":["33la"]},{"type":"scatter","value":50,"color":0,"size_w":1,"size_h":1,"loca":["m2HJ","mJ3J"]},{"type":"laser-","value":50,"color":0,"size_w":1,"size_h":1,"loca":["m2H2","m2HH"]}],"props2":[{"type":"missile","value":50,"color":2,"size_w":1,"size_h":1,"loca":["3mF3","m1F3"]}],"tasks":[{"type":"magnet","count":1},{"type":"puzzle","count":2},{"type":"orange","count":12}]}